LughaatNLP/LughaatNLP.py
LughaatNLP/NER_Urdu.py
LughaatNLP/POS_urdu.py
LughaatNLP/TextSummarization.py
LughaatNLP/UrduChatbot.py
LughaatNLP/UrduSpeech.py
LughaatNLP/Urdu_Lemma.json
LughaatNLP/__init__.py
LughaatNLP/max_length.pkl
LughaatNLP/ner_tag2index.pkl
LughaatNLP/ner_word2index.pkl
LughaatNLP/pos_model.pth
LughaatNLP/stopwords.json
LughaatNLP/tag2index.pkl
LughaatNLP/tokenizer.json
LughaatNLP/urdu_ner_model.pth
LughaatNLP/word2index.pkl
LughaatNLP-1.3.1.dist-info/METADATA
LughaatNLP-1.3.1.dist-info/WHEEL
LughaatNLP-1.3.1.dist-info/entry_points.txt
LughaatNLP-1.3.1.dist-info/top_level.txt
LughaatNLP-1.3.1.dist-info/RECORD
