Metadata-Version: 2.1
Name: LughaatNLP
Version: 1.3.1
Summary: A Python package for natural language processing tasks for the Urdu language, including normalization, part-of-speech (POS) tagging, named entity recognition (NER), stemming, lemmatization, tokenization, and stopword removal , text-to-speech , speech-to-text, summarization.
Home-page: https://github.com/MuhammadNoman76/LughaatNLP
Author: Muhammad Noman
Author-email: muhammadnomanshafiq76@gmail.com
License: MIT
Project-URL: Source, https://github.com/MuhammadNoman76/LughaatNLP
Project-URL: Issue Tracker, https://github.com/MuhammadNoman76/LughaatNLP/issues
Project-URL: LinkedIn, https://www.linkedin.com/in/muhammad-noman76
Project-URL: YouTube Channel, https://www.youtube.com/playlist?list=PL4tcmUwDtJEIHZhAZ3XP9U6ZJzaS4RFbd
Project-URL: Google Colab, https://colab.research.google.com/drive/1lLaUBiFq61-B7GyQ0wdNg9FyLCraAcDU?usp=sharing
Project-URL: Geeksforgeeks, https://www.geeksforgeeks.org/lughaatnlp-a-powerful-urdu-language-preprocessing-library/
Project-URL: LughaatNLP Blog, https://lughaatnlp.blogspot.com/2024/04/mastering-urdu-text-processing.html
Project-URL: Medium, https://medium.com/@muhammadnomanshafiq76/introducing-lughaatnlp-a-powerful-urdu-language-preprocessing-library-488af74d3dde
Keywords: urdu nlp natural language processing text processing tokenization stemming lemmatization stopwords morphological-analysis nlp urdu LughaatNLP urdunlp UrduNLP urduhack stanza natural-language-processing text-processing language-processing preprocessing stemming lemmatization tokenization stopwords
Classifier: Development Status :: 5 - Production/Stable
Classifier: Intended Audience :: Developers
Classifier: Intended Audience :: Science/Research
Classifier: License :: OSI Approved :: MIT License
Classifier: Programming Language :: Python :: 3
Classifier: Programming Language :: Python :: 3.6
Classifier: Programming Language :: Python :: 3.7
Classifier: Programming Language :: Python :: 3.8
Classifier: Programming Language :: Python :: 3.9
Classifier: Topic :: Scientific/Engineering :: Artificial Intelligence
Classifier: Topic :: Text Processing :: Linguistic
Classifier: Natural Language :: Urdu
Requires-Dist: python-Levenshtein
Requires-Dist: numpy
Requires-Dist: scikit-learn
Requires-Dist: scipy
Requires-Dist: gtts
Requires-Dist: SpeechRecognition
Requires-Dist: pydub
Requires-Dist: torch ==2.5.1
Requires-Dist: torch >=1.9.0
Requires-Dist: transformers >=4.11.0
Requires-Dist: pandas >=1.3.0
Requires-Dist: tqdm >=4.62.0
